MANIFEST.in
README
setup.py
dudac.egg-info/PKG-INFO
dudac.egg-info/SOURCES.txt
dudac.egg-info/dependency_links.txt
dudac.egg-info/entry_points.txt
dudac.egg-info/not-zip-safe
dudac.egg-info/top_level.txt
dudaclient/__init__.py
dudaclient/dudac.Make
dudaclient/git.py
dudaclient/main.py
dudaclient/utils.py