Metadata-Version: 1.1
Name: dudac
Version: 0.20
Summary: DudaC is a command line interface for Duda I/O web services framework
Home-page: http://duda.io
Author: Eduardo Silva
Author-email: edsiper@gmail.com
License: LGPLv2
Download-URL: http://duda.io/releases/duda-client/dudac-0.20.tar.gz
Keywords: HTTP monkey duda server framework linux websocket nosql
Platform: UNKNOWN
Classifier: Development Status :: 5 - Production/Stable
Classifier: License :: OSI Approved :: GNU Lesser General Public License v2 (LGPLv2)
Classifier: Programming Language :: Python
Classifier: Environment :: Console
Classifier: Intended Audience :: Developers
Classifier: Topic :: Software Development :: Build Tools
